midiSynth/__init__.py
midiSynth/synth.py
midiSynth-0.3.dist-info/LICENSE
midiSynth-0.3.dist-info/METADATA
midiSynth-0.3.dist-info/WHEEL
midiSynth-0.3.dist-info/top_level.txt
midiSynth-0.3.dist-info/RECORD
